pytechecker/__init__.py
pytechecker-1.0.1.dist-info/LICENSE
pytechecker-1.0.1.dist-info/METADATA
pytechecker-1.0.1.dist-info/WHEEL
pytechecker-1.0.1.dist-info/top_level.txt
pytechecker-1.0.1.dist-info/RECORD
