Metadata-Version: 2.1
Name: pytechecker
Version: 1.0.1
Summary: A lightweight type/object checking library.
Home-page: https://github.com/dcronqvist/pytechecker
Author: dcronqvist
Author-email: daniel@dcronqvist.se
License: UNKNOWN
Keywords: payload,api,type check,api payload,flask payload,flask,flask api,object check,check
Platform: UNKNOWN
Classifier: Programming Language :: Python :: 3
Classifier: License :: OSI Approved :: MIT License
Classifier: Operating System :: OS Independent
Requires-Python: >=3.6
